limao/limao.py
limao/run_limao.py
limao-0.1.0.dist-info/LICENSE
limao-0.1.0.dist-info/METADATA
limao-0.1.0.dist-info/WHEEL
limao-0.1.0.dist-info/entry_points.txt
limao-0.1.0.dist-info/RECORD
