Metadata-Version: 2.1
Name: limao
Version: 0.1.0
Summary: 
License: MIT
Author: Daniel O'Hanlon
Author-email: dpohanlon@gmail.com
Requires-Python: >=3.9,<4.0
Classifier: License :: OSI Approved :: MIT License
Classifier: Programming Language :: Python :: 3
Classifier: Programming Language :: Python :: 3.9
Classifier: Programming Language :: Python :: 3.10
Classifier: Programming Language :: Python :: 3.11
Requires-Dist: bng-latlon (>=1.1,<2.0)
Requires-Dist: earthpy (>=0.9.4,<0.10.0)
Requires-Dist: h5py (>=3.9.0,<4.0.0)
Requires-Dist: matplotlib (>=3.7.2,<4.0.0)
Requires-Dist: numpy (>=1.25.2,<2.0.0)
Requires-Dist: pandas (>=2.0.3,<3.0.0)
Requires-Dist: pysolar (>=0.11,<0.12)
Requires-Dist: rioxarray (>=0.14.1,<0.15.0)
Requires-Dist: scikit-image (>=0.21.0,<0.22.0)
Requires-Dist: seaborn (>=0.12.2,<0.13.0)
Requires-Dist: tqdm (>=4.65.0,<5.0.0)
